{
  "$schema": "../config-schema.json",
  "docs": [
    {
      "id": "explorernrelease",
      "title": "Release Notes",
      "url": "cloud/explore/relnotes",
      "metadata": {
        "platform": ["Cloud"],
        "product": ["Explore"],
        "version": ["latest"],
        "subject": ["Release notes"]
      },
      "environments": ["dev", "staging", "prod"],
      "displayOnLandingPages": true,
      "indexForSearch": true,
      "public": false,
      "internal": false,
      "earlyAccess": false
    },
    {
      "id": "exploreusingrelease",
      "title": "Application Guide",
      "url": "cloud/explore/app",
      "metadata": {
        "platform": ["Cloud"],
        "product": ["Explore"],
        "version": ["latest"],
        "subject": ["Features and functionality"]
      },
      "environments": ["dev", "staging", "prod"],
      "displayOnLandingPages": true,
      "indexForSearch": true,
      "public": false,
      "internal": false,
      "earlyAccess": false
    },
    {
      "id": "exploredatadictrelease",
      "title": "Data Dictionaries",
      "url": "cloud/explore/datadict",
      "metadata": {
        "platform": ["Cloud"],
        "product": ["Explore"],
        "version": ["latest"],
        "subject": ["Development"]
      },
      "environments": ["dev", "staging", "prod"],
      "displayOnLandingPages": true,
      "indexForSearch": true,
      "public": false,
      "internal": false,
      "earlyAccess": false
    }
  ]
}
