{
  "$schema": "../config-schema.json",
  "docs": [
    {
      "id": "keti",
      "title": "Keti Cloud Common Auth",
      "url": "internal/keti/latest",
      "metadata": {
        "platform": ["Cloud"],
        "product": ["Keti", "Internal Docs"],
        "version": ["latest"],
        "language": "en"
      },
      "environments": ["staging"],
      "displayOnLandingPages": true,
      "indexForSearch": true,
      "public": false,
      "internal": true,
      "earlyAccess": false
    },
    {
      "id": "dma",
      "title": "DMA - Database migration to Aurora",
      "url": "internal/dma/latest",
      "metadata": {
        "platform": ["Cloud"],
        "product": ["Internal Docs"],
        "version": ["latest"],
        "language": "en"
      },
      "environments": ["staging"],
      "displayOnLandingPages": true,
      "indexForSearch": true,
      "public": false,
      "internal": true,
      "earlyAccess": false
    },
    {
      "id": "gch",
      "title": "Guidewire Cloud Home",
      "url": "internal/gch/latest",
      "metadata": {
        "platform": ["Cloud"],
        "product": ["Internal Docs"],
        "version": ["latest"],
        "language": "en"
      },
      "environments": ["staging"],
      "displayOnLandingPages": true,
      "indexForSearch": true,
      "public": false,
      "internal": true,
      "earlyAccess": false
    },
    {
      "id": "binrepo",
      "title": "Binary Repository",
      "url": "internal/binrepo/latest",
      "metadata": {
        "platform": ["Cloud"],
        "product": ["Internal Docs", "BinRepo"],
        "version": ["latest"],
        "language": "en"
      },
      "environments": ["staging"],
      "displayOnLandingPages": true,
      "indexForSearch": true,
      "public": false,
      "internal": true,
      "earlyAccess": false
    },
    {
      "id": "nebula",
      "title": "Nebula Atmos Persistence",
      "url": "internal/nebula/latest",
      "metadata": {
        "platform": ["Cloud"],
        "product": ["Internal Docs", "Nebula"],
        "version": ["latest"],
        "language": "en"
      },
      "environments": ["staging"],
      "displayOnLandingPages": true,
      "indexForSearch": true,
      "public": false,
      "internal": true,
      "earlyAccess": false
    },
    {
      "id": "atlas",
      "title": "Atlas",
      "url": "internal/atlas/latest",
      "metadata": {
        "platform": ["Cloud"],
        "product": ["Internal Docs", "Atlas"],
        "version": ["latest"],
        "language": "en"
      },
      "environments": ["staging"],
      "displayOnLandingPages": true,
      "indexForSearch": true,
      "public": false,
      "internal": true,
      "earlyAccess": false
    },
    {
      "id": "helios",
      "title": "Helios",
      "url": "internal/helios/latest",
      "metadata": {
        "platform": ["Cloud"],
        "product": ["Internal Docs", "Helios"],
        "version": ["latest"],
        "language": "en"
      },
      "environments": ["staging"],
      "displayOnLandingPages": true,
      "indexForSearch": true,
      "public": false,
      "internal": true,
      "earlyAccess": false
    },
    {
      "id": "heliosclient",
      "title": "Helios Client",
      "url": "internal/heliosclient/latest",
      "metadata": {
        "platform": ["Cloud"],
        "product": ["Internal Docs", "Helios"],
        "version": ["latest"],
        "language": "en"
      },
      "environments": ["staging"],
      "displayOnLandingPages": true,
      "indexForSearch": true,
      "public": false,
      "internal": true,
      "earlyAccess": false
    },
    {
      "id": "mithril",
      "title": "Mithril",
      "url": "internal/mithril/latest",
      "metadata": {
        "platform": ["Cloud"],
        "product": ["Internal Docs"],
        "version": ["latest"],
        "language": "en"
      },
      "environments": ["staging"],
      "displayOnLandingPages": true,
      "indexForSearch": true,
      "public": false,
      "internal": true,
      "earlyAccess": false
    },
    {
      "id": "nova",
      "title": "Nova",
      "url": "internal/nova/latest",
      "metadata": {
        "platform": ["Cloud"],
        "product": ["Internal Docs", "Nova"],
        "version": ["latest"],
        "language": "en"
      },
      "environments": ["staging"],
      "displayOnLandingPages": true,
      "indexForSearch": true,
      "public": false,
      "internal": true,
      "earlyAccess": false
    },
    {
      "id": "msk",
      "title": "MSK",
      "url": "internal/msk/latest",
      "metadata": {
        "platform": ["Cloud"],
        "product": ["Internal Docs", "MSK"],
        "version": ["latest"],
        "language": "en"
      },
      "environments": ["staging"],
      "displayOnLandingPages": true,
      "indexForSearch": true,
      "public": false,
      "internal": true,
      "earlyAccess": false
    },
    {
      "id": "mskadmin",
      "title": "MSK Admin",
      "url": "internal/mskadmin/latest",
      "metadata": {
        "platform": ["Cloud"],
        "product": ["Internal Docs", "MSK Admin"],
        "version": ["latest"],
        "language": "en"
      },
      "environments": ["staging"],
      "displayOnLandingPages": true,
      "indexForSearch": true,
      "public": false,
      "internal": true,
      "earlyAccess": false
    },
    {
      "id": "sonarqube",
      "title": "SonarQube",
      "url": "internal/sonarqube/latest",
      "metadata": {
        "platform": ["Cloud"],
        "product": ["Internal Docs", "SonarQube"],
        "version": ["latest"],
        "language": "en"
      },
      "environments": ["staging"],
      "displayOnLandingPages": true,
      "indexForSearch": true,
      "public": false,
      "internal": true,
      "earlyAccess": false
    },
    {
      "id": "goldenimage",
      "title": "Golden Image",
      "url": "internal/goldenimage/latest",
      "metadata": {
        "platform": ["Cloud"],
        "product": ["Internal Docs", "Golden Image"],
        "version": ["latest"],
        "language": "en"
      },
      "environments": ["staging"],
      "displayOnLandingPages": true,
      "indexForSearch": true,
      "public": false,
      "internal": true,
      "earlyAccess": false
    }
  ]
}
