{
  "$schema": "../config-schema.json",
  "docs": [
    {
      "id": "isconfigupgradetools320jaJP",
      "title": "InsuranceSuite Configuration Upgrade Tools ja-JP",
      "url": "isconfigupgradetools/ja-JP/320",
      "metadata": {
        "platform": ["Cloud", "Self-managed"],
        "product": ["InsuranceSuite Configuration Upgrade Tools"],
        "version": ["3.2.0"],
        "release": ["Aspen", "Banff", "Cortina"]
      },
      "environments": ["int", "staging"],
      "displayOnLandingPages": true,
      "indexForSearch": true,
      "public": false,
      "internal": false,
      "earlyAccess": false
    },
    {
      "id": "isconfigupgradetools450",
      "title": "InsuranceSuite Configuration Upgrade Tools",
      "url": "isconfigupgradetools/450",
      "metadata": {
        "platform": ["Cloud", "Self-managed"],
        "product": ["InsuranceSuite Configuration Upgrade Tools"],
        "version": ["4.5.0"],
        "release": ["Aspen", "Banff", "Cortina", "Dobson", "Elysian", "Flaine"]
      },
      "environments": ["int", "staging"],
      "displayOnLandingPages": true,
      "indexForSearch": true,
      "public": false,
      "internal": false,
      "earlyAccess": false
    },
    {
      "id": "isconfigupgradetools440",
      "title": "InsuranceSuite Configuration Upgrade Tools",
      "url": "isconfigupgradetools/440",
      "metadata": {
        "platform": ["Cloud", "Self-managed"],
        "product": ["InsuranceSuite Configuration Upgrade Tools"],
        "version": ["4.4.0"],
        "release": ["Aspen", "Banff", "Cortina", "Dobson", "Elysian", "Flaine"]
      },
      "environments": ["int", "staging", "prod"],
      "displayOnLandingPages": true,
      "indexForSearch": true,
      "public": false,
      "internal": false,
      "earlyAccess": false
    },
    {
      "id": "isconfigupgradetools430",
      "title": "InsuranceSuite Configuration Upgrade Tools",
      "url": "isconfigupgradetools/430",
      "metadata": {
        "platform": ["Cloud", "Self-managed"],
        "product": ["InsuranceSuite Configuration Upgrade Tools"],
        "version": ["4.3.0"],
        "release": ["Aspen", "Banff", "Cortina", "Dobson", "Elysian"]
      },
      "environments": ["int", "staging", "prod"],
      "displayOnLandingPages": true,
      "indexForSearch": true,
      "public": false,
      "internal": false,
      "earlyAccess": false
    },
    {
      "id": "isconfigupgradetools420",
      "title": "InsuranceSuite Configuration Upgrade Tools",
      "url": "isconfigupgradetools/420",
      "metadata": {
        "platform": ["Cloud", "Self-managed"],
        "product": ["InsuranceSuite Configuration Upgrade Tools"],
        "version": ["4.2.0"],
        "release": ["Aspen", "Banff", "Cortina", "Dobson"]
      },
      "environments": ["dev", "staging", "prod"],
      "displayOnLandingPages": true,
      "indexForSearch": true,
      "public": false,
      "internal": false,
      "earlyAccess": false
    },
    {
      "id": "isconfigupgradetools410",
      "title": "InsuranceSuite Configuration Upgrade Tools",
      "url": "isconfigupgradetools/410",
      "metadata": {
        "platform": ["Cloud", "Self-managed"],
        "product": ["InsuranceSuite Configuration Upgrade Tools"],
        "version": ["4.1.0"],
        "release": ["Aspen", "Banff", "Cortina", "Dobson"]
      },
      "environments": ["dev", "staging", "prod"],
      "displayOnLandingPages": true,
      "indexForSearch": true,
      "public": false,
      "internal": false,
      "earlyAccess": false
    },
    {
      "id": "isconfigupgradetools400",
      "title": "InsuranceSuite Configuration Upgrade Tools",
      "url": "isconfigupgradetools/400",
      "metadata": {
        "platform": ["Cloud", "Self-managed"],
        "product": ["InsuranceSuite Configuration Upgrade Tools"],
        "version": ["4.0.0"],
        "release": ["Aspen", "Banff", "Cortina", "Dobson"]
      },
      "environments": ["dev", "staging", "prod"],
      "displayOnLandingPages": true,
      "indexForSearch": true,
      "public": false,
      "internal": false,
      "earlyAccess": false
    },
    {
      "id": "isconfigupgradetools330",
      "title": "InsuranceSuite Configuration Upgrade Tools",
      "url": "isconfigupgradetools/330",
      "metadata": {
        "platform": ["Cloud", "Self-managed"],
        "product": ["InsuranceSuite Configuration Upgrade Tools"],
        "version": ["3.3.0"],
        "release": ["Aspen", "Banff", "Cortina", "Dobson"]
      },
      "environments": ["int", "staging", "prod"],
      "displayOnLandingPages": true,
      "indexForSearch": true,
      "public": false,
      "internal": false,
      "earlyAccess": false
    },
    {
      "id": "isconfigupgradetools310",
      "title": "InsuranceSuite Configuration Upgrade Tools",
      "url": "isconfigupgradetools/310",
      "metadata": {
        "platform": ["Cloud", "Self-managed"],
        "product": ["InsuranceSuite Configuration Upgrade Tools"],
        "version": ["3.1.0"],
        "release": ["Aspen", "Banff", "Cortina"]
      },
      "environments": ["int", "staging", "prod"],
      "displayOnLandingPages": true,
      "indexForSearch": true,
      "public": false,
      "internal": false,
      "earlyAccess": false
    }
  ]
}
