{
  "$schema": "/frontend/page-schema.json",
  "title": "Global Content - Germany",
  "template": "page",
  "class": "twoColumns",
  "selector": {
    "label": "Select release",
    "selectedItem": "3.6",
    "items": [
      {
        "label": "3.8",
        "page": "../3.8"
      },
      {
        "label": "3.7",
        "page": "../3.7"
      }
    ]
  },
  "items": [
    {
      "label": "Release Notes",
      "class": "subject releaseNotes",
      "items": [
        {
          "label": "Release Notes",
          "id": "midipgrnen36"
        },
        {
          "label": "Release Notes (German)",
          "id": "midipgrnde36"
        }
      ]
    },
    {
      "label": "Features and functionality",
      "class": "subject featuresAndFunctionality",
      "items": [
        {
          "label": "Application Guide",
          "id": "midipgapp36"
        },
        {
          "label": "Application Guide (German)",
          "id": "midipgappde36"
        },
        {
          "label": "Implementation",
          "id": "midipgimpl36"
        }
      ]
    },
    {
      "label": "Installation",
      "class": "subject installation",
      "items": [
        {
          "label": "Installation",
          "id": "midipginstall36"
        }
      ]
    },
    {
      "label": "Glossary",
      "class": "subject glossary",
      "items": [
        {
          "label": "Glossary",
          "id": "midipgglossary36"
        }
      ]
    }
  ],
  "search_filters": {
    "language": ["en", "de"]
  }
}
