{
  "$schema": "../../config-schema.json",
  "docs": [
    {
      "id": "isbc202310frFRreleasenotes",
      "title": "Release Notes fr",
      "displayTitle": "Notes sur la version",
      "url": "fr/cloud/bc/202310/releasenotes",
      "metadata": {
        "platform": ["Cloud"],
        "product": ["BillingCenter"],
        "version": ["2023.10"],
        "release": ["Innsbruck"],
        "subject": ["Release notes"],
        "language": "fr"
      },
      "environments": ["staging", "prod"],
      "displayOnLandingPages": true,
      "indexForSearch": true,
      "public": false,
      "internal": false,
      "earlyAccess": false
    },
    {
      "id": "isbc202310frFRupdate",
      "title": "Update fr",
      "displayTitle": "Guide de mise à niveau",
      "url": "fr/cloud/bc/202310/update",
      "metadata": {
        "platform": ["Cloud"],
        "product": ["BillingCenter"],
        "version": ["2023.10"],
        "release": ["Innsbruck"],
        "subject": ["Installation"],
        "language": "fr"
      },
      "environments": ["staging", "prod"],
      "displayOnLandingPages": true,
      "indexForSearch": true,
      "public": false,
      "internal": false,
      "earlyAccess": false
    },
    {
      "id": "isbc202310frFRapp",
      "title": "Application Guide fr",
      "displayTitle": "Guide de l'application BillingCenter",
      "url": "fr/cloud/bc/202310/app",
      "metadata": {
        "platform": [ "Cloud" ],
        "product": [ "BillingCenter" ],
        "version": [ "2023.10" ],
        "release": [ "Innsbruck" ],
        "subject": [ "Features and functionality" ],
        "language": "fr"
      },
      "environments": [ "staging" ],
      "displayOnLandingPages": true,
      "indexForSearch": true,
      "public": false,
      "internal": false,
      "earlyAccess": false
    },
    {
      "id": "iscc202310frFRreleasenotes",
      "title": "Release Notes fr",
      "displayTitle": "Notes sur la version",
      "url": "fr/cloud/cc/202310/releasenotes",
      "metadata": {
        "platform": ["Cloud"],
        "product": ["ClaimCenter"],
        "version": ["2023.10"],
        "release": ["Innsbruck"],
        "subject": ["Release notes"],
        "language": "fr"
      },
      "environments": ["staging", "prod"],
      "displayOnLandingPages": true,
      "indexForSearch": true,
      "public": false,
      "internal": false,
      "earlyAccess": false
    },
    {
      "id": "iscc202310frFRupdate",
      "title": "Update fr",
      "displayTitle": "Guide de mise à niveau",
      "url": "fr/cloud/cc/202310/update",
      "metadata": {
        "platform": ["Cloud"],
        "product": ["ClaimCenter"],
        "version": ["2023.10"],
        "release": ["Innsbruck"],
        "subject": ["Installation"],
        "language": "fr"
      },
      "environments": ["staging", "prod"],
      "displayOnLandingPages": true,
      "indexForSearch": true,
      "public": false,
      "internal": false,
      "earlyAccess": false
    },
    {
      "id": "iscc202310frFRapp",
      "title": "Application Guide fr",
      "displayTitle": "Guide de l'application ClaimCenter",
      "url": "fr/cloud/cc/202310/app",
      "metadata": {
        "platform": [ "Cloud" ],
        "product": [ "ClaimCenter" ],
        "version": [ "2023.10" ],
        "release": [ "Innsbruck" ],
        "subject": [ "Features and functionality" ],
        "language": "fr"
      },
      "environments": [ "staging" ],
      "displayOnLandingPages": true,
      "indexForSearch": true,
      "public": false,
      "internal": false,
      "earlyAccess": false
    },
    {
      "id": "ispc202310frFRreleasenotes",
      "title": "Release Notes fr",
      "displayTitle": "Notes sur la version",
      "url": "fr/cloud/pc/202310/releasenotes",
      "metadata": {
        "platform": ["Cloud"],
        "product": ["PolicyCenter"],
        "version": ["2023.10"],
        "release": ["Innsbruck"],
        "subject": ["Release notes"],
        "language": "fr"
      },
      "environments": ["staging", "prod"],
      "displayOnLandingPages": true,
      "indexForSearch": true,
      "public": false,
      "internal": false,
      "earlyAccess": false
    },
    {
      "id": "ispc202310frFRupdate",
      "title": "Update fr",
      "displayTitle": "Guide de mise à niveau",
      "url": "fr/cloud/pc/202310/update",
      "metadata": {
        "platform": ["Cloud"],
        "product": ["PolicyCenter"],
        "version": ["2023.10"],
        "release": ["Innsbruck"],
        "subject": ["Installation"],
        "language": "fr"
      },
      "environments": ["staging", "prod"],
      "displayOnLandingPages": true,
      "indexForSearch": true,
      "public": false,
      "internal": false,
      "earlyAccess": false
    },
    {
      "id": "ispc202310frFRapp",
      "title": "Application Guide fr",
      "displayTitle": "Guide de l'application PolicyCenter",
      "url": "fr/cloud/pc/202310/app",
      "metadata": {
        "platform": [ "Cloud" ],
        "product": [ "PolicyCenter" ],
        "version": [ "2023.10" ],
        "release": [ "Innsbruck" ],
        "subject": [ "Features and functionality" ],
        "language": "fr"
      },
      "environments": [ "staging" ],
      "displayOnLandingPages": true,
      "indexForSearch": true,
      "public": false,
      "internal": false,
      "earlyAccess": false
    }
  ]
}
